bendis/__init__.py
bendis/robotic_arm_env.py
bendis-0.8.0.dist-info/METADATA
bendis-0.8.0.dist-info/WHEEL
bendis-0.8.0.dist-info/top_level.txt
bendis-0.8.0.dist-info/RECORD
