Metadata-Version: 2.2
Name: bendis
Version: 0.8.0
Summary: A custom robotic arm environment for reinforcement learning.
Home-page: https://your-repository-link.com
Author: Your Name
Author-email: your.email@example.com
Classifier: Programming Language :: Python :: 3
Classifier: License :: OSI Approved :: MIT License
Classifier: Operating System :: OS Independent
Requires-Dist: gym
Requires-Dist: pybullet
Requires-Dist: numpy
Requires-Dist: opencv-python
Dynamic: author
Dynamic: author-email
Dynamic: classifier
Dynamic: home-page
Dynamic: requires-dist
Dynamic: summary
